secrets_env/__init__.py
secrets_env/__main__.py
secrets_env/assets/error.html
secrets_env/assets/oidc-success.html
secrets_env/config/__init__.py
secrets_env/config/lookup.py
secrets_env/config/parser.py
secrets_env/config/reader.py
secrets_env/console/__init__.py
secrets_env/console/commands/__init__.py
secrets_env/console/commands/completion.py
secrets_env/console/commands/run.py
secrets_env/console/commands/set.py
secrets_env/console/commands/shell.py
secrets_env/console/commands/show.py
secrets_env/console/core.py
secrets_env/console/decorators.py
secrets_env/console/loggings.py
secrets_env/console/shells/__init__.py
secrets_env/console/shells/base.py
secrets_env/console/shells/posix.py
secrets_env/console/shells/windows.py
secrets_env/exceptions.py
secrets_env/provider.py
secrets_env/providers/__init__.py
secrets_env/providers/debug.py
secrets_env/providers/kubernetes/__init__.py
secrets_env/providers/kubernetes/kubectl.py
secrets_env/providers/kubernetes/models.py
secrets_env/providers/onepassword/__init__.py
secrets_env/providers/onepassword/models.py
secrets_env/providers/onepassword/op.py
secrets_env/providers/plain.py
secrets_env/providers/teleport/__init__.py
secrets_env/providers/teleport/config.py
secrets_env/providers/vault/__init__.py
secrets_env/providers/vault/api.py
secrets_env/providers/vault/auth/__init__.py
secrets_env/providers/vault/auth/base.py
secrets_env/providers/vault/auth/jwt.py
secrets_env/providers/vault/auth/kubernetes.py
secrets_env/providers/vault/auth/oidc.py
secrets_env/providers/vault/auth/token.py
secrets_env/providers/vault/auth/userpass.py
secrets_env/providers/vault/config.py
secrets_env/py.typed
secrets_env/realms/__init__.py
secrets_env/realms/poetry/__init__.py
secrets_env/realms/poetry/cleo.py
secrets_env/realms/server.py
secrets_env/realms/shellingham.py
secrets_env/realms/subprocess.py
secrets_env/utils.py
secrets_env/version.py
secrets_env-1.0.5.dist-info/METADATA
secrets_env-1.0.5.dist-info/WHEEL
secrets_env-1.0.5.dist-info/entry_points.txt
secrets_env-1.0.5.dist-info/RECORD
